NetkillerDocbook/README.md
NetkillerDocbook/__init__.py
NetkillerDocbook/__main__.py
NetkillerDocbook/file.epub
NetkillerDocbook/index.html
NetkillerDocbook/css/__init__.py
NetkillerDocbook/css/annotations.css
NetkillerDocbook/css/main.css
NetkillerDocbook/css/normalize.css
NetkillerDocbook/css/popup.css
NetkillerDocbook/font/__init__.py
NetkillerDocbook/font/fontello.eot
NetkillerDocbook/font/fontello.svg
NetkillerDocbook/font/fontello.ttf
NetkillerDocbook/font/fontello.woff
NetkillerDocbook/img/__init__.py
NetkillerDocbook/img/annotator-glyph-sprite.png
NetkillerDocbook/img/annotator-icon-sprite.png
NetkillerDocbook/img/apple-touch-icon.png
NetkillerDocbook/img/cancelfullscreen.png
NetkillerDocbook/img/close.png
NetkillerDocbook/img/fullscreen.png
NetkillerDocbook/img/loader.gif
NetkillerDocbook/img/menu-icon.png
NetkillerDocbook/img/save.png
NetkillerDocbook/img/saved.png
NetkillerDocbook/img/settings-s.png
NetkillerDocbook/img/settings.png
NetkillerDocbook/img/star.png
NetkillerDocbook/js/__init__.py
NetkillerDocbook/js/epub.js
NetkillerDocbook/js/epub.min.js
NetkillerDocbook/js/epub.min.map
NetkillerDocbook/js/hooks.min.js
NetkillerDocbook/js/hooks.min.map
NetkillerDocbook/js/reader.js
NetkillerDocbook/js/reader.js.map
NetkillerDocbook/js/reader.min.js
NetkillerDocbook/js/reader.min.map
NetkillerDocbook/js/hooks/__init__.py
NetkillerDocbook/js/hooks/extensions/__init__.py
NetkillerDocbook/js/hooks/extensions/highlight.js
NetkillerDocbook/js/libs/__init__.py
NetkillerDocbook/js/libs/jquery.min.js
NetkillerDocbook/js/libs/localforage.min.js
NetkillerDocbook/js/libs/screenfull.js
NetkillerDocbook/js/libs/screenfull.min.js
NetkillerDocbook/js/libs/zip.min.js
NetkillerDocbook/js/plugins/__init__.py
NetkillerDocbook/js/plugins/hypothesis.js
NetkillerDocbook/js/plugins/search.js
netkiller_docbook-2024.3.5.0.dist-info/METADATA
netkiller_docbook-2024.3.5.0.dist-info/WHEEL
netkiller_docbook-2024.3.5.0.dist-info/entry_points.txt
netkiller_docbook-2024.3.5.0.dist-info/top_level.txt
netkiller_docbook-2024.3.5.0.dist-info/RECORD
